pgorm/__init__.py
postg_orm-0.0.1.dist-info/METADATA
postg_orm-0.0.1.dist-info/WHEEL
postg_orm-0.0.1.dist-info/top_level.txt
postg_orm-0.0.1.dist-info/RECORD
